cosmos_sdk/__init__.py
cosmos_sdk/client/__init__.py
cosmos_sdk/client/lcd/__init__.py
cosmos_sdk/client/lcd/api/__init__.py
cosmos_sdk/client/lcd/api/_base.py
cosmos_sdk/client/lcd/api/auth.py
cosmos_sdk/client/lcd/api/authz.py
cosmos_sdk/client/lcd/api/bank.py
cosmos_sdk/client/lcd/api/distribution.py
cosmos_sdk/client/lcd/api/feegrant.py
cosmos_sdk/client/lcd/api/gov.py
cosmos_sdk/client/lcd/api/ibc.py
cosmos_sdk/client/lcd/api/ibc_transfer.py
cosmos_sdk/client/lcd/api/mint.py
cosmos_sdk/client/lcd/api/slashing.py
cosmos_sdk/client/lcd/api/staking.py
cosmos_sdk/client/lcd/api/tendermint.py
cosmos_sdk/client/lcd/api/tx.py
cosmos_sdk/client/lcd/api/wasm.py
cosmos_sdk/client/lcd/lcdclient.py
cosmos_sdk/client/lcd/lcdutils.py
cosmos_sdk/client/lcd/params.py
cosmos_sdk/client/lcd/wallet.py
cosmos_sdk/client/localterra.py
cosmos_sdk/core/__init__.py
cosmos_sdk/core/auth/__init__.py
cosmos_sdk/core/auth/data/__init__.py
cosmos_sdk/core/auth/data/account.py
cosmos_sdk/core/auth/data/base_account.py
cosmos_sdk/core/auth/data/base_vesting_account.py
cosmos_sdk/core/auth/data/continuous_vesting_account.py
cosmos_sdk/core/auth/data/delayed_vesting_account.py
cosmos_sdk/core/auth/data/periodic_vesting_account.py
cosmos_sdk/core/auth/msgs/__init__.py
cosmos_sdk/core/auth/msgs/msg_create_periodic_vesting_account.py
cosmos_sdk/core/auth/msgs/msg_create_vesting_account.py
cosmos_sdk/core/auth/msgs/msg_donate_all_vesting_tokens.py
cosmos_sdk/core/authz/__init__.py
cosmos_sdk/core/authz/data.py
cosmos_sdk/core/authz/msgs.py
cosmos_sdk/core/bank/__init__.py
cosmos_sdk/core/bank/msgs.py
cosmos_sdk/core/bech32.py
cosmos_sdk/core/block.py
cosmos_sdk/core/broadcast.py
cosmos_sdk/core/coin.py
cosmos_sdk/core/coins.py
cosmos_sdk/core/compact_bit_array.py
cosmos_sdk/core/crisis/__init__.py
cosmos_sdk/core/crisis/msgs.py
cosmos_sdk/core/deposit.py
cosmos_sdk/core/distribution/__init__.py
cosmos_sdk/core/distribution/msgs.py
cosmos_sdk/core/distribution/proposals.py
cosmos_sdk/core/fee.py
cosmos_sdk-0.0.3.dist-info/LICENSE
cosmos_sdk-0.0.3.dist-info/WHEEL
cosmos_sdk-0.0.3.dist-info/METADATA
cosmos_sdk-0.0.3.dist-info/RECORD
